sr2t/__about__.py
sr2t/__main__.py
sr2t/data/nessus_autoclassify.yaml
sr2t/data/nessus_http.yaml
sr2t/data/nessus_rdp.yaml
sr2t/data/nessus_smb.yaml
sr2t/data/nessus_snmp.yaml
sr2t/data/nessus_ssh.yaml
sr2t/data/nessus_tls.yaml
sr2t/data/nessus_x509.yaml
sr2t/data/nmap_http.yaml
sr2t/data/nmap_rdp.yaml
sr2t/data/nmap_ssh.yaml
sr2t/data/nmap_ssl.yaml
sr2t/data/testssl.yaml
sr2t/handlers/__init__.py
sr2t/handlers/output_handler.py
sr2t/handlers/parser_handler.py
sr2t/parsers/__init__.py
sr2t/parsers/dirble.py
sr2t/parsers/fortify.py
sr2t/parsers/nessus.py
sr2t/parsers/nikto.py
sr2t/parsers/nmap.py
sr2t/parsers/testssl.py
sr2t/shared/__init__.py
sr2t/shared/export.py
sr2t/shared/utils.py
sr2t-0.6.0.dist-info/METADATA
sr2t-0.6.0.dist-info/WHEEL
sr2t-0.6.0.dist-info/entry_points.txt
sr2t-0.6.0.dist-info/licenses/LICENSE
sr2t-0.6.0.dist-info/RECORD
