Metadata-Version: 2.4
Name: sr2t
Version: 0.6.0
Summary: Converts scanning reports to a tabular format
Project-URL: Bug Reports, https://gitlab.com/0bs1d1an/sr2t/issues
Project-URL: Homepage, https://gitlab.com/0bs1d1an/sr2t
Project-URL: Source, https://gitlab.com/0bs1d1an/sr2t/
Author-email: "Guido Kroon (@0bs1d1an)" <gkroon@maelstrom.ninja>
License-Expression: GPL-3.0-only
License-File: LICENSE
Classifier: Development Status :: 4 - Beta
Classifier: Intended Audience :: Information Technology
Classifier: Intended Audience :: System Administrators
Classifier: License :: OSI Approved :: GNU General Public License v3 (GPLv3)
Classifier: Programming Language :: Python
Classifier: Programming Language :: Python :: 3.8
Classifier: Programming Language :: Python :: 3.9
Classifier: Programming Language :: Python :: 3.10
Classifier: Programming Language :: Python :: 3.11
Classifier: Programming Language :: Python :: 3.12
Classifier: Programming Language :: Python :: 3.13
Classifier: Programming Language :: Python :: Implementation :: CPython
Classifier: Programming Language :: Python :: Implementation :: PyPy
Classifier: Topic :: Security
Requires-Python: >=3.8
Requires-Dist: cryptography
Requires-Dist: defusedxml
Requires-Dist: prettytable
Requires-Dist: pyyaml
Requires-Dist: requests
Requires-Dist: xlsxwriter
